smstats/__init__.py
smstats/config.py
smstats/custom.py
smstats/manager.py
smstats/postutils.py
smstats/utils.py
smstats-1.0.0.dist-info/LICENSE
smstats-1.0.0.dist-info/METADATA
smstats-1.0.0.dist-info/WHEEL
smstats-1.0.0.dist-info/top_level.txt
smstats-1.0.0.dist-info/RECORD
