Metadata-Version: 2.1
Name: smstats
Version: 1.0.0
Summary: SuperMetrics Assignment package
Home-page: https://github.com/manishgupta-78/smstats
Author: Manish Gupta
Author-email: gupta_manish@outlook.com
License: MIT
Platform: any
Classifier: Development Status :: 5 - Production/Stable
Classifier: Environment :: Console
Classifier: License :: OSI Approved :: MIT License
Classifier: Operating System :: OS Independent
Classifier: Programming Language :: Python
Classifier: Programming Language :: Python :: 3
Classifier: Programming Language :: Python :: 3 :: Only
Classifier: Programming Language :: Python :: 3.9
Classifier: Programming Language :: Python :: 3.10
Requires-Python: >=3.9
License-File: LICENSE
Requires-Dist: requests
